auris_tools/__init__.py
auris_tools/configuration.py
auris_tools/databaseHandlers.py
auris_tools/geminiHandler.py
auris_tools/officeWordHandler.py
auris_tools/storageHandler.py
auris_tools/textractHandler.py
auris_tools/utils.py
auris_tools-0.2.0.dist-info/METADATA
auris_tools-0.2.0.dist-info/WHEEL
auris_tools-0.2.0.dist-info/RECORD
