Metadata-Version: 2.4
Name: auris_tools
Version: 0.2.0
Summary: The swiss knife tools to coordinates cloud frameworks with an easy for Auris platforms
Author: Antonio Senra
Author-email: acsenrafilho@gmail.com
Requires-Python: >=3.10,<4.0
Classifier: Programming Language :: Python :: 3
Classifier: Programming Language :: Python :: 3.10
Classifier: Programming Language :: Python :: 3.11
Classifier: Programming Language :: Python :: 3.12
Classifier: Programming Language :: Python :: 3.13
Classifier: Programming Language :: Python :: 3.14
Requires-Dist: boto3 (>=1.40.29,<2.0.0)
Requires-Dist: dotenv (>=0.9.9,<0.10.0)
Requires-Dist: google-generativeai (>=0.8.5,<0.9.0)
Requires-Dist: python-docx (>=1.2.0,<2.0.0)
Requires-Dist: rich (>=14.1.0,<15.0.0)
